{
  "_type": "https://in-toto.io/Statement/v1",
  "predicate": {
    "buildDefinition": {
      "buildType": "https://github.com/VOID-TECHNOLOGY-INC/PyBun/.github/workflows/release.yml",
      "externalParameters": {
        "ref": "refs/tags/v0.1.18",
        "sha": "093c5bced170cb92537a5d9d615917484bf2eee7",
        "workflow": "Release Build"
      },
      "internalParameters": {},
      "resolvedDependencies": [
        {
          "digest": {
            "sha1": "093c5bced170cb92537a5d9d615917484bf2eee7"
          },
          "uri": "git+https://github.com/VOID-TECHNOLOGY-INC/PyBun@093c5bced170cb92537a5d9d615917484bf2eee7"
        }
      ]
    },
    "runDetails": {
      "builder": {
        "id": "https://github.com/VOID-TECHNOLOGY-INC/PyBun/.github/workflows/release.yml"
      },
      "metadata": {
        "finishedOn": "2026-06-02T09:31:58Z",
        "invocationId": "https://github.com/VOID-TECHNOLOGY-INC/PyBun/actions/runs/26810937717",
        "runAttempt": "1",
        "startedOn": "2026-06-02T09:31:58Z"
      }
    }
  },
  "predicateType": "https://slsa.dev/provenance/v1",
  "subject": [
    {
      "digest": {
        "sha256": "131a5f28ebdd5e9e6c535cb22913a4ea11312c3401babf0c984b34bc548c33fa"
      },
      "name": "pybun-aarch64-apple-darwin.tar.gz"
    },
    {
      "digest": {
        "sha256": "910ac179bcb769459b106bb782f02b6bef693760ca4e4923300af8cf041a8827"
      },
      "name": "pybun-x86_64-unknown-linux-gnu.tar.gz"
    },
    {
      "digest": {
        "sha256": "f0a32b4e86bbd4286925c0c06eb7173f1320b8fbe596a38bfbe3a64e383d14bc"
      },
      "name": "pybun-aarch64-unknown-linux-gnu.tar.gz"
    },
    {
      "digest": {
        "sha256": "43a9a90b078b3dee1e0636394a8ee9f40081b87533e235674339478cb72a2201"
      },
      "name": "pybun-x86_64-unknown-linux-musl.tar.gz"
    },
    {
      "digest": {
        "sha256": "560150de196ec0b8673ae76d9ac5a0bc6fb0054b874c1e092fef973e5a9f127d"
      },
      "name": "pybun-x86_64-apple-darwin.tar.gz"
    },
    {
      "digest": {
        "sha256": "0737ea4d9bba0efb6e9797d100ea6f2491404f46d02fdbc2e37e55bfafdb96ee"
      },
      "name": "pybun-x86_64-pc-windows-msvc.zip"
    }
  ]
}
