{
  "version": "0.1.12",
  "description": "Rust-based single-binary Python toolchain.",
  "homepage": "https://github.com/VOID-TECHNOLOGY-INC/PyBun",
  "license": "MIT",
  "architecture": {
    "64bit": {
      "url": "https://github.com/VOID-TECHNOLOGY-INC/PyBun/releases/download/v0.1.12/pybun-x86_64-pc-windows-msvc.zip",
      "hash": "dbab442f34283e34eb09f67155c61e080aba05e264f5a7eb8bc01679eecba71e"
    }
  },
  "bin": [
    "pybun.exe",
    [
      "pybun.exe",
      "pybun-cli"
    ]
  ],
  "extract_dir": "pybun-x86_64-pc-windows-msvc",
  "checkver": {
    "url": "https://github.com/VOID-TECHNOLOGY-INC/PyBun/releases/latest",
    "regex": "tag/v([\\d.]+)"
  },
  "autoupdate": {
    "architecture": {
      "64bit": {
        "url": "https://github.com/VOID-TECHNOLOGY-INC/PyBun/releases/download/v$version/pybun-x86_64-pc-windows-msvc.zip"
      }
    }
  }
}
